fnsapi/__init__.py
fnsapi/api.py
fnsapi/query.py
fnsapi/storage/__init__.py
fnsapi/storage/env.py
fnsapi/storage/ini.py
fnsapi/storage/sqlite3.py
tests/__init__.py
tests/api.py
tests/storage_ini.py
fnsapi-0.0.3.dist-info/LICENSE
fnsapi-0.0.3.dist-info/METADATA
fnsapi-0.0.3.dist-info/WHEEL
fnsapi-0.0.3.dist-info/top_level.txt
fnsapi-0.0.3.dist-info/RECORD
