Metadata-Version: 2.1
Name: fnsapi
Version: 0.0.3
Summary: Russian Federal Tax Service API connector
Home-page: https://github.com/QortexDevs/fnsapi
Author: Qortex Devs
Author-email: it@qortex.ru
License: UNKNOWN
Platform: UNKNOWN
Classifier: Programming Language :: Python :: 3
Classifier: License :: OSI Approved :: MIT License
Classifier: Operating System :: OS Independent
Requires-Python: >=3.6
